[
  {
    "Nombre": "Juan Perez",
    "AsignaturasCompletadas": 3,
    "Solicitudes": 3,
    "Asignaturas": [
      {
        "Nombre": "Matemáticas Avanzadas",
        "Sala": "A-1",
        "Bloque": 1,
        "Dia": "Miercoles",
        "Satisfaccion": 10
      },
      {
        "Nombre": "Programación Basica",
        "Sala": "A-1",
        "Bloque": 3,
        "Dia": "Miercoles",
        "Satisfaccion": 10
      },
      {
        "Nombre": "Codigo Binario",
        "Sala": "A-1",
        "Bloque": 5,
        "Dia": "Miercoles",
        "Satisfaccion": 5
      }
    ]
  }
]